<?xml version="1.0" encoding="UTF-8" standalone="yes"?>
<?xml-stylesheet type="text/xsl" href="modx.prosilver.en.xsl"?>
<!--NOTICE: Please open this file in your web browser. If presented with a security warning, you may safely tell it to allow the blocked content.-->
<!--For security purposes, please check: http://www.phpbb.com/mods/ for the latest version of this MOD.\nAlthough MODs are checked before being allowed in the MODs Database there is no guarantee that there are no security problems within the MOD.\nNo support will be given for MODs not found within the MODs Database which can be found at http://www.phpbb.com/mods/-->
<mod xmlns:xsi="http://www.w3.org/2001/XMLSchema-instance" xmlns="http://www.phpbb.com/mods/xml/modx-1.2.5.xsd">
	<header>
		<meta name="generator" content="MODX file generated with PP MODX Creator by tumba25 (online version)"/>
		<license><![CDATA[http://opensource.org/licenses/gpl-license.php GNU General Public License v2]]></license>
		<title lang="en"><![CDATA[XFire Mod]]></title>
		<description lang="en"><![CDATA[Displays a small image of users that have entered in an XFire account in viewtopic (when clicked on will take a user to the members XFire Profile) as well as their profile (XFire mini-profile found just above signature panel, when clicked on will take the member to that users xfire profile).]]></description>
		<author-notes lang="en"><![CDATA[Comes in both subSilver2 and prosilver flavors.]]></author-notes>
		<author-group>
			<author>
				<realname><![CDATA[Tyler]]></realname>
				<username><![CDATA[bprsk8r4272]]></username>
				<homepage><![CDATA[http://gotskillslounge.com]]></homepage>
				<email><![CDATA[prosk8er@gotskillslounge.com]]></email>
			</author>
			<author>
				<realname><![CDATA[Richard McGirr]]></realname>
				<username><![CDATA[RMcGirr83]]></username>
				<homepage><![CDATA[http://rmcgirr83.org]]></homepage>
				<email><![CDATA[rmcgirr83@rmcgirr83.org]]></email>
				<contributions-group>
					<contributions status="past" from="2008-12-31" to="2009-03-02" position="Origional Author"/>
				</contributions-group>
			</author>
		</author-group>
		<mod-version>1.0.4</mod-version>
		<installation>
			<level>easy</level>
			<time>1200</time>
			<target-version>3.0.10</target-version>
		</installation>
		<history>
			<entry>
				<date>2011-08-26</date>
				<rev-version>1.0.4</rev-version>
				<changelog lang="en">
					<change><![CDATA[got rid of old image added prosilver and subsilver2 style images]]></change>
				</changelog>
			</entry>
			<entry>
				<date>2009-03-02</date>
				<rev-version>1.0.3</rev-version>
				<changelog lang="en">
					<change><![CDATA[Added db_update file, no more phpmyadmin.  Added FAQ entry.  MODx 1.2.2 HTML changes]]></change>
				</changelog>
			</entry>
			<entry>
				<date>2009-01-14</date>
				<rev-version>1.0.2</rev-version>
				<changelog lang="en">
					<change><![CDATA[Tightened up code for ucp_profile.php and html file]]></change>
				</changelog>
			</entry>
			<entry>
				<date>2009-01-08</date>
				<rev-version>1.0.1</rev-version>
				<changelog lang="en">
					<change><![CDATA[Added abiity to select styling of mini-profile for xfire]]></change>
				</changelog>
			</entry>
			<entry>
				<date>2009-01-09</date>
				<rev-version>1.0.1a</rev-version>
				<changelog lang="en">
					<change><![CDATA[Fixed image error in viewtopic_body.html]]></change>
				</changelog>
			</entry>
			<entry>
				<date>2008-12-31</date>
				<rev-version>1.0.0</rev-version>
				<changelog lang="en">
					<change><![CDATA[Initial Release]]></change>
				</changelog>
			</entry>
		</history>
		<link-group>
			<link type="template" href="./contrib/subsilver2.xml" lang="en">subsilver2</link>
			<link type="contrib" href="./contrib/update_103_to_104/install_mod.xml" lang="en">Update 1.0.3 to 1.0.4</link>
			<link type="contrib" href="./contrib/required_by_registration/install_mod.xml" lang="en">Required By Registration</link>
			<link type="contrib" href="./contrib/xfire_status_on_viewmessage/install_mod.xml" lang="en">Xfire Mod status on viewmessage</link>
			<link type="contrib" href="./contrib/xfire_status_on_viewtopic/install_mod.xml" lang="en">Xfire Mod status on viewtopic</link>
			<link type="contrib" href="./contrib/xfire_viewmessage/install_mod.xml" lang="en">Xfire Mod for viewmessage</link>
		</link-group>
	</header>
	<action-group>
		<copy>
			<file from="root/language/en/mods/info_acp_xfire.php" to="language/en/mods/info_acp_xfire.php"/>
			<file from="root/language/en/mods/xfire.php" to="language/en/mods/xfire.php"/>
			<file from="root/includes/mods/xfire_mod.php" to="includes/mods/xfire_mod.php"/>
			<file from="root/styles/prosilver/imageset/icon_contact_xfire.gif" to="styles/prosilver/imageset/icon_contact_xfire.gif"/>
			<file from="root/umil/*.*" to="umil/*.*"/>
			<file from="root/xfire_install.php" to="xfire_install.php"/>
		</copy>
		<open src="memberlist.php">
			<edit>
				<find><![CDATA[$user->setup(array('memberlist',]]></find>
				<action type="after-add"><![CDATA[// BEGIN xfire mod
$user->add_lang('mods/xfire');
include($phpbb_root_path . 'includes/mods/xfire_mod.' . $phpEx);
//END xfire mod]]></action>
			</edit>
			<edit>
				<find><![CDATA[case 'viewprofile':]]></find>
				<find><![CDATA[$template->assign_vars(array(]]></find>
				<action type="before-add"><![CDATA[		//BEGIN xfire mod
		if (!empty($member['user_xfire']))
		{
			$xfire_style = XFIRE_BG;
			if ($member['user_xfire_style'] == XFIRE_SHADOW)
			{
				$xfire_style = XFIRE_SH;
			}
			elseif ($member['user_xfire_style'] == XFIRE_COMBAT)
			{
				$xfire_style = XFIRE_CO;
			}
			elseif ($member['user_xfire_style'] == XFIRE_SCIFI)
			{
				$xfire_style = XFIRE_SF;
			}
			elseif ($member['user_xfire_style'] == XFIRE_FANTASY)
			{
				$xfire_style = XFIRE_OS;
			}
			elseif ($member['user_xfire_style'] == XFIRE_WOW)
			{
				$xfire_style = XFIRE_WO;
			}
		}
		// END xfire mod]]></action>
			</edit>
			<edit>
				<find><![CDATA['SIGNATURE'		=>]]></find>
				<action type="after-add"><![CDATA[// BEGIN xfire mod
			'XFIRE'		=> (!empty($member['user_xfire'])) ? $member['user_xfire'] : '',
			'XFIRE_STYLE'   => (!empty($member['user_xfire'])) ? $xfire_style : XFIRE_BG,
// END xfire mod]]></action>
			</edit>
		</open>
		<open src="viewtopic.php">
			<edit>
				<find><![CDATA[$auth->acl($user->data);]]></find>
				<action type="after-add"><![CDATA[// BEGIN xfire mod
$user->add_lang('mods/xfire');
// END xfire mod]]></action>
			</edit>
			<edit>
				<find><![CDATA[	'MSN_IMG' 			=> $user->img('icon_contact_msnm', 'MSNM'),]]></find>
				<action type="after-add"><![CDATA[// BEGIN xfire mod
	'XFIRE_IMG' 			=> $user->img('icon_contact_xfire', 'XFIRE'),
// END xfire mod]]></action>
			</edit>
			<edit>
				<find><![CDATA[				'msn'				=> '',]]></find>
				<action type="after-add"><![CDATA[// BEGIN xfire mod
				'xfire'			=> '',
// END xfire mod]]></action>
			</edit>
			<edit>
				<find><![CDATA[				'msn'			=> ($row['user_msnm'] && $auth->acl_get('u_sendim')) ? append_sid("{$phpbb_root_path}memberlist.$phpEx", "mode=contact&amp;action=msnm&amp;u=$poster_id") : '',]]></find>
				<action type="after-add"><![CDATA[// BEGIN xfire mod
				'xfire'			=> (isset($row['user_xfire']) && $auth->acl_get('u_sendim'))  ? $row['user_xfire'] : '',
//END xfire mod]]></action>
			</edit>
			<edit>
				<find><![CDATA[		'U_MSN'			=> $user_cache[$poster_id]['msn'],]]></find>
				<action type="after-add"><![CDATA[// BEGIN xfire mod
		'U_XFIRE'			=> $user_cache[$poster_id]['xfire'],
//END xfire mod]]></action>
			</edit>
		</open>
		<open src="adm/style/acp_users_profile.html">
			<edit>
				<find><![CDATA[	<dl>
		<dt><label for="msn">{L_UCP_MSNM}:</label></dt>
		<dd><input type="text" id="msn" name="msn" value="{MSN}" /></dd>
	</dl>]]></find>
				<action type="after-add"><![CDATA[	<dl>
		<dt><label for="xfire">{L_XFIRE}:</label></dt>
		<dd><input type="text" id="xfire" name="xfire" value="{XFIRE}" /></dd>
	</dl>]]></action>
			</edit>
		</open>
		<open src="includes/acp/acp_styles.php">
			<edit>
				<find><![CDATA[			'buttons'	=> array(
				'icon_back_top']]></find>
				<inline-edit>
					<inline-find><![CDATA[, 'icon_contact_www']]></inline-find>
					<inline-action type="after-add"><![CDATA[, 'icon_contact_xfire']]></inline-action>
				</inline-edit>
			</edit>
		</open>
		<open src="includes/acp/acp_users.php">
			<edit>
				<find><![CDATA[			case 'profile':]]></find>
				<find><![CDATA[				$cp = new custom_profile();]]></find>
				<action type="after-add"><![CDATA[				// xfire mod
				$user->add_lang('mods/xfire');]]></action>
			</edit>
			<edit>
				<find><![CDATA[					'msn'			=> request_var('msn', $user_row['user_msnm']),]]></find>
				<action type="after-add"><![CDATA[					// xfire mod
					'xfire'			=> (isset($user_row['user_xfire'])) ? strtolower(request_var('xfire', $user_row['user_xfire'])) : '',]]></action>
			</edit>
			<edit>
				<find><![CDATA[						'msn'			=> array('string', true, 5, 255),]]></find>
				<action type="after-add"><![CDATA[						// xfire mod
						'xfire'			=> array('string', true, 4, 25),]]></action>
			</edit>
			<edit>
				<find><![CDATA[							'user_msnm'		=> $data['msn'],]]></find>
				<action type="after-add"><![CDATA[							// xfire mod
							'user_xfire'		=> $data['xfire'],]]></action>
			</edit>
			<edit>
				<find><![CDATA[					'MSN'			=> $data['msn'],]]></find>
				<action type="after-add"><![CDATA[					// xfire mod
					'XFIRE'			=> $data['xfire'],]]></action>
			</edit>
		</open>
		<open src="includes/ucp/ucp_profile.php">
			<edit>
				<find><![CDATA[				$cp_data = $cp_error = array();]]></find>
				<action type="after-add"><![CDATA[// BEGIN xfire mod
				$user->add_lang('mods/xfire');
//END xfire mod]]></action>
			</edit>
			<edit>
				<find><![CDATA[					'msn'			=> request_var('msn', $user->data['user_msnm']),]]></find>
				<action type="after-add"><![CDATA[// BEGIN xfire mod
					'xfire'                 => (isset($user_row['user_xfire'])) ? strtolower(request_var('xfire', $user_row['user_xfire'])) : '',
					'xfire_style'           => request_var('xfire_style', $user->data['user_xfire_style']),
//END xfire mod]]></action>
			</edit>
			<edit>
				<find><![CDATA[						'msn'			=> array('string', true, 5, 255),]]></find>
				<action type="after-add"><![CDATA[//BEGIN xfire mod
						'xfire'			=> array('string', true, 4, 25),
//END xfire mod]]></action>
			</edit>
			<edit>
				<find><![CDATA[							'user_msnm'		=> $data['msn'],]]></find>
				<action type="after-add"><![CDATA[//BEGIN xfire mod
							'user_xfire'		=> $data['xfire'],
							'user_xfire_style'      => $data['xfire_style'],
//END xfire mod]]></action>
			</edit>
			<edit>
				<find><![CDATA[					'MSN'		=> $data['msn'],]]></find>
				<action type="after-add"><![CDATA[//BEGIN xfire mod
					'XFIRE'			=> $data['xfire'],
					'XFIRE_STYLE'		=> $data['xfire_style'],
					'XFIRE_EXPLAIN'		=> sprintf($user->lang['XFIRE_EXPLAIN'], '<a href="' . append_sid("{$phpbb_root_path}faq.$phpEx") . '">', '</a>'),
//END xfire mod]]></action>
			</edit>
		</open>
		<open src="language/en/help_faq.php">
			<edit>
				<find><![CDATA[		1 => 'To find your list of attachments that you have uploaded, go to your User Control Panel and follow the links to the attachments section.'
	),]]></find>
				<action type="after-add"><![CDATA[	array(
		0 => '--',
		1 => 'XFire'
	),
	array(
		0 => 'What is XFire?',
		1 => '<a href="http://www.xfire.com">XFire</a> is a free gaming tool that automatically keeps track of when and where gamers are playing PC games online and lets their friends join them easily. It doesn’t matter which online game your friends are playing, which server browser they are using, or which gaming service they’re playing on; Xfire is intelligent enough to recognize where your friends are at any time.',
	),
	array(
		0 => 'How can I add users to my XFire account?',
		1 => 'You can add users to your XFire account by simply clicking on the links found when viewing a registered users profile.'
	),
]]></action>
			</edit>
		</open>
		<open src="styles/prosilver/imageset/imageset.cfg">
			<edit>
				<find><![CDATA[img_icon_contact_msnm = icon_contact_msnm.gif*20*20]]></find>
				<action type="after-add"><![CDATA[img_icon_contact_xfire = icon_contact_xfire.gif*20*20]]></action>
			</edit>
		</open>
		<open src="styles/prosilver/template/memberlist_view.html">
			<edit>
				<find><![CDATA[<!-- IF SIGNATURE -->]]></find>
				<action type="before-add"><![CDATA[<!-- IF XFIRE -->
<div class="panel bg1">
	<div class="inner"><span class="corners-top"><span></span></span>
		<h3>{L_XFIRE}</h3>
		<div class="postbody">
			<div class="xfire" style="border-top:none; margin-top: 0;"><a href="http://profile.xfire.com/{XFIRE}"><img src="http://miniprofile.xfire.com/bg/{XFIRE_STYLE}/type/0/{XFIRE}.png" width="440" height="111" alt="" /></a><br /><div style="font-size: 1em;"><a href="xfire:add_friend?user={XFIRE}">{L_ADD_XFIRE_USER}</a> | <a href="http://www.xfire.com/download/">{L_DOWNLOAD_XFIRE}</a></div></div>
		</div>
	<span class="corners-bottom"><span></span></span></div>
</div>
<!-- ENDIF -->]]></action>
			</edit>
		</open>
		<open src="styles/prosilver/template/ucp_profile_profile_info.html">
			<edit>
				<find><![CDATA[	<dl>
		<dt><label for="msn">{L_UCP_MSNM}:</label></dt>
		<dd><input type="text" name="msn" id="msn" maxlength="255" value="{MSN}" class="inputbox" /></dd>
	</dl>]]></find>
				<action type="after-add"><![CDATA[	<dl>
		<dt><label for="xfire">{L_XFIRE}:</label><br /><span>{XFIRE_EXPLAIN}</span></dt>
		<dd><input type="text" name="xfire" id="xfire" maxlength="25" value="{XFIRE}" class="inputbox" /></dd>
	</dl>
	<dl>
		<dt>{L_XFIRE_STYLE}:<br /><span>{L_XFIRE_STYLE_EXPLAIN}</span></dt>
		<dd>
			<label for="xfire_style1"><input type="radio" name="xfire_style" id="xfire_style1" value="1" style="margin: 2px;"<!-- IF XFIRE_STYLE eq 1 --> checked="checked"<!-- ENDIF --> /> {L_XFIRE_SHADOW}</label>
			<label for="xfire_style2"><input type="radio" name="xfire_style" id="xfire_style2" value="2" style="margin: 2px;"<!-- IF XFIRE_STYLE eq 2 --> checked="checked"<!-- ENDIF --> /> {L_XFIRE_COMBAT}</label>
			<label for="xfire_style3"><input type="radio" name="xfire_style" id="xfire_style3" value="3" style="margin: 2px;"<!-- IF XFIRE_STYLE eq 3 --> checked="checked"<!-- ENDIF --> /> {L_XFIRE_SCIFI}</label>
			<label for="xfire_style4"><input type="radio" name="xfire_style" id="xfire_style4" value="4" style="margin: 2px;"<!-- IF XFIRE_STYLE eq 4 --> checked="checked"<!-- ENDIF --> /> {L_XFIRE_FANTASY}</label>
			<label for="xfire_style5"><input type="radio" name="xfire_style" id="xfire_style5" value="5" style="margin: 2px;"<!-- IF XFIRE_STYLE eq 5 --> checked="checked"<!-- ENDIF --> /> {L_XFIRE_WOW}</label>
			<label for="xfire_style6"><input type="radio" name="xfire_style" id="xfire_style6" value="6" style="margin: 2px;"<!-- IF XFIRE_STYLE eq 6 --> checked="checked"<!-- ENDIF --> /> {L_XFIRE_DEFAULT}</label>
		</dd>
	</dl>]]></action>
			</edit>
		</open>
		<open src="styles/prosilver/template/viewtopic_body.html">
			<edit>
				<find><![CDATA[<!-- IF postrow.U_PM or postrow.U_EMAIL]]></find>
				<inline-edit>
					<inline-find><![CDATA[postrow.U_JABBER]]></inline-find>
					<inline-action type="after-add"><![CDATA[ or postrow.U_XFIRE]]></inline-action>
				</inline-edit>
			</edit>
			<edit>
				<find><![CDATA[					<!-- IF postrow.U_MSN --><li class="msnm-icon"><a href="{postrow.U_MSN}" onclick="popup(this.href, 550, 320); return false;" title="{L_MSNM}"><span>{L_MSNM}</span></a></li><!-- ENDIF -->]]></find>
				<action type="after-add"><![CDATA[  					<!-- IF postrow.U_XFIRE --><li class="xfire-icon"><a href="http://profile.xfire.com/{postrow.U_XFIRE}" title="{L_XFIRE}"><span>{L_XFIRE}</span></a></li><!-- ENDIF -->]]></action>
			</edit>
		</open>
		<open src="styles/prosilver/theme/buttons.css">
			<edit>
				<find><![CDATA[.msnm-icon, .msnm-icon a			{ background: none top left no-repeat; }]]></find>
				<action type="after-add"><![CDATA[.xfire-icon, .xfire-icon a			{ background: none top left no-repeat; }]]></action>
			</edit>
			<edit>
				<find><![CDATA[ul.profile-icons li.msnm-icon	{ width: {IMG_ICON_CONTACT_MSNM_WIDTH}px; height: {IMG_ICON_CONTACT_MSNM_HEIGHT}px; }]]></find>
				<action type="after-add"><![CDATA[ul.profile-icons li.xfire-icon	{ width: {IMG_ICON_CONTACT_XFIRE_WIDTH}px; height: {IMG_ICON_CONTACT_XFIRE_HEIGHT}px; }]]></action>
			</edit>
		</open>
		<open src="styles/prosilver/theme/colours.css">
			<edit>
				<find><![CDATA[.signature]]></find>
				<action type="before-add"><![CDATA[.xfire a, .xfire a:visited, .xfire a:active, .xfire a:hover {
	background-color: transparent;
}]]></action>
			</edit>
			<edit>
				<find><![CDATA[.msnm-icon, .msnm-icon a			{ background-image: url("{IMG_ICON_CONTACT_MSNM_SRC}"); }]]></find>
				<action type="after-add"><![CDATA[.xfire-icon, .xfire-icon a			{ background-image: url("{IMG_ICON_CONTACT_XFIRE_SRC}"); }]]></action>
			</edit>
		</open>
		<php-installer><![CDATA[xfire_install.php]]></php-installer>
		<diy-instructions lang="en"><![CDATA[Login to your forum as admin, browse to the xfire_install.php file.  Once run, delete the file, purge the cache, refresh the template, theme and imageset in the ACP.]]></diy-instructions>
	</action-group>
</mod>
